Metadata-Version: 2.1
Name: nicellm
Version: 0.0.1
Summary: NiceLLM is a wrangler of API connections of Large Language Models (LLMs) in Python.
Home-page: https://github.com/cnavarreteliz/nicellm
Author: cnavarreteliz
Author-email: cnavarreteliz@gmail.com
Classifier: Programming Language :: Python :: 3
Classifier: Programming Language :: Python :: 3.7
Classifier: Programming Language :: Python :: 3.8
Classifier: Programming Language :: Python :: 3.9
Classifier: Programming Language :: Python :: 3.10
Classifier: Programming Language :: Python :: 3.11
License-File: LICENSE.md
